{
  "features": [
    {
      "type": "Feature",
      "properties": {
        "title": "MCQ supermarket",
        "description": "Coventry Village, Morley"
      },
      "geometry": {
        "coordinates": [
          115.892678,
          -31.894706
        ],
        "type": "Point"
      },
      "id": "d861ca3febf537f55b01e3c7457d0b09"
    }
  ],
  "type": "FeatureCollection"
}
